naptha_sdk/cli.py
naptha_sdk/client/grpc_server_pb2.py
naptha_sdk/client/grpc_server_pb2_grpc.py
naptha_sdk/client/hub.py
naptha_sdk/client/naptha.py
naptha_sdk/client/node.py
naptha_sdk/configs.py
naptha_sdk/inference.py
naptha_sdk/module_manager.py
naptha_sdk/modules/agent.py
naptha_sdk/modules/environment.py
naptha_sdk/modules/kb.py
naptha_sdk/modules/memory.py
naptha_sdk/modules/orchestrator.py
naptha_sdk/modules/tool.py
naptha_sdk/schemas.py
naptha_sdk/scrape.py
naptha_sdk/secrets.py
naptha_sdk/storage/schemas.py
naptha_sdk/storage/storage_client.py
naptha_sdk/user.py
naptha_sdk/utils.py
naptha_sdk-1.0.5.dist-info/METADATA
naptha_sdk-1.0.5.dist-info/WHEEL
naptha_sdk-1.0.5.dist-info/entry_points.txt
naptha_sdk-1.0.5.dist-info/RECORD
