Metadata-Version: 2.3
Name: naptha-sdk
Version: 1.0.5
Summary: Python SDK for interacting with Naptha nodes and building distributed AI modules
Author: Richard Blythman
Author-email: richardblythman@gmail.com
Requires-Python: >=3.10,<=3.13
Classifier: Programming Language :: Python :: 3
Classifier: Programming Language :: Python :: 3.10
Classifier: Programming Language :: Python :: 3.11
Classifier: Programming Language :: Python :: 3.12
Classifier: Programming Language :: Python :: 3.13
Requires-Dist: cryptography (>=44.0.0,<45.0.0)
Requires-Dist: ecdsa (>=0.19.0,<0.20.0)
Requires-Dist: gitpython (>=3.1.43,<4.0.0)
Requires-Dist: grpcio (>=1.68.1,<2.0.0)
Requires-Dist: grpcio-tools (>=1.68.1,<2.0.0)
Requires-Dist: httpx (>=0.27.0,<0.28.0)
Requires-Dist: ipfshttpclient (>=0.7.0,<0.8.0)
Requires-Dist: payments-py (>=0.1.2,<0.2.0)
Requires-Dist: pyjwt (>=2.8.0,<3.0.0)
Requires-Dist: pytest (>=8.3.4,<9.0.0)
Requires-Dist: python-dotenv (>=1.0.1,<2.0.0)
Requires-Dist: pytz (>=2024.1,<2025.0)
Requires-Dist: pyyaml (>=6.0.1,<7.0.0)
Requires-Dist: surrealdb (>=0.3.2,<0.4.0)
Requires-Dist: tabulate (>=0.9.0,<0.10.0)
Requires-Dist: tomlkit (>=0.13.2,<0.14.0)
